drdoc/__init__.py
drdoc/drdoc.py
drdoc-0.1.1.dist-info/licenses/LICENSE
drdoc-0.1.1.dist-info/METADATA
drdoc-0.1.1.dist-info/WHEEL
drdoc-0.1.1.dist-info/entry_points.txt
drdoc-0.1.1.dist-info/top_level.txt
drdoc-0.1.1.dist-info/RECORD
