Metadata-Version: 2.4
Name: drdoc
Version: 0.1.1
Summary: A documentation processing tool for identifying and correcting errors in markdown, reStructuredText, and plain text files
Author-email: Murat Keceli <keceli@gmail.com>
License: MIT License
Project-URL: Homepage, https://github.com/keceli/drdoc
Project-URL: Repository, https://github.com/keceli/drdoc
Keywords: documentation,markdown,rst,text-processing,ai-assisted-editing
Requires-Python: >=3.8
License-File: LICENSE
Requires-Dist: requests>=2.25.0
Provides-Extra: dev
Requires-Dist: pytest; extra == "dev"
Requires-Dist: black; extra == "dev"
Requires-Dist: flake8; extra == "dev"
Dynamic: license-file
